mp3norm
