Metadata-Version: 2.1
Name: mp3norm
Version: 0.5
Summary: Extract tags from filename and/or fetch album name/cover from Google Search
Home-page: https://github.com/Docheinstein/mp3norm
Author: Stefano Dottore
Author-email: docheinstein@gmail.com
License: MIT
Keywords: mp3norm
Platform: UNKNOWN
Requires-Python: >=3.6
